MANIFEST.in
setup.py
src/twitter2backlog/__init__.py
src/twitter2backlog/tmpl/timeline.tmpl
test/test_twitter2backlog.py
twitter2backlog.egg-info/PKG-INFO
twitter2backlog.egg-info/SOURCES.txt
twitter2backlog.egg-info/dependency_links.txt
twitter2backlog.egg-info/entry_points.txt
twitter2backlog.egg-info/requires.txt
twitter2backlog.egg-info/top_level.txt