Metadata-Version: 1.0
Name: twitter2backlog
Version: 0.0.2
Summary: a small utility to collect twitter mentions in a certain period and post them to backlog as an issue
Home-page: https://github.com/tksmd/twitter2backlog
Author: Takashi SOMEDA
Author-email: someda@isenshi.com
License: Apache Licence Version 2.0
Keywords: backlog twitter
Platform: any
Classifier: Operating System :: OS Independent
Classifier: Environment :: Console
Classifier: Programming Language :: Python
Classifier: License :: OSI Approved :: Apache Software License
Classifier: Development Status :: 2 - Pre-Alpha
Classifier: Intended Audience :: Developers
Classifier: Topic :: Internet :: WWW/HTTP :: Dynamic Content :: CGI Tools/Libraries
Classifier: Topic :: Software Development :: Libraries :: Python Modules
Classifier: Topic :: Utilities
